custom_onecyclelr/__init__.py
custom_onecyclelr/config.py
custom_onecyclelr/scheduler.py
custom_onecyclelr-0.2.0.dist-info/LICENSE
custom_onecyclelr-0.2.0.dist-info/METADATA
custom_onecyclelr-0.2.0.dist-info/WHEEL
custom_onecyclelr-0.2.0.dist-info/RECORD
