Metadata-Version: 2.3
Name: custom-onecyclelr
Version: 0.2.0
Summary: A Custom PyTorch implementation of the OneCycleLR learning rate scheduler. (With some modifications)
License: MIT License
Keywords: pytorch,deep-learning,optimizer,lr scheduler,OneCycleLR
Author: AidinHamedi
Author-email: aidin.hamediasl@gmail.com
Requires-Python: >=3.10
Classifier: Development Status :: 4 - Beta
Classifier: License :: OSI Approved :: MIT License
Classifier: Intended Audience :: Education
Classifier: Intended Audience :: Developers
Classifier: Intended Audience :: Science/Research
Classifier: Programming Language :: Python :: 3
Classifier: Programming Language :: Python :: 3.10
Classifier: Programming Language :: Python :: 3.11
Classifier: Programming Language :: Python :: 3.12
Classifier: Programming Language :: Python :: 3.13
Classifier: Operating System :: OS Independent
Classifier: Topic :: Scientific/Engineering
Classifier: Topic :: Scientific/Engineering :: Artificial Intelligence
Classifier: Topic :: Software Development
Classifier: Topic :: Software Development :: Libraries
Classifier: Topic :: Software Development :: Libraries :: Python Modules
Requires-Dist: torch (>=2.0)
Project-URL: Homepage, https://github.com/AidinHamedi/Custom-OneCycleLr-Pytorch
Project-URL: Repository, https://github.com/AidinHamedi/Custom-OneCycleLr-Pytorch
